onering/__init__.py
onering/context.py
onering/dirutils.py
onering/errors.py
onering/graph.py
onering/loader.py
onering/resolver.py
onering/utils.py
onering/actions/__init__.py
onering/actions/base.py
onering/actions/dirs.py
onering/actions/gen.py
onering/actions/loaders.py
onering/console/__init__.py
onering/console/courier.py
onering/console/default.py
onering/console/dirs.py
onering/console/orc.py
onering/console/pegasus.py
onering/console/platform.py
onering/console/runner.py
onering/console/utils.py
onering/core/__init__.py
onering/core/exprs.py
onering/core/functions.py
onering/core/interfaces.py
onering/core/platforms.py
onering/core/projections.py
onering/core/resolvers.py
onering/core/transformers.py
onering/core/utils.py
onering/data/templates/backends/java/mutable_pojo
onering/data/templates/transformers/java/NOTES
onering/data/templates/transformers/java/Prob1
onering/data/templates/transformers/java/Prob2
onering/data/templates/transformers/java/default_statement
onering/data/templates/transformers/java/default_transformer_group
onering/data/templates/transformers/java/immutable_ast
onering/data/templates/transformers/java/instruction
onering/data/templates/transformers/java/java
onering/data/templates/transformers/java/java_common
onering/data/templates/transformers/java/macros
onering/data/templates/transformers/java/mutable_ast
onering/data/templates/transformers/java/source_ast
onering/data/templates/transformers/java/to_immutable_pojo
onering/data/templates/transformers/java/to_mutable_pojo
onering/dsl/__init__.py
onering/dsl/errors.py
onering/dsl/lexer.py
onering/dsl/parser/__init__.py
onering/dsl/parser/tokstream.py
onering/dsl/parser/rules/__init__.py
onering/dsl/parser/rules/annotations.py
onering/dsl/parser/rules/derivations.py
onering/dsl/parser/rules/functions.py
onering/dsl/parser/rules/interfaces.py
onering/dsl/parser/rules/misc.py
onering/dsl/parser/rules/platforms.py
onering-0.0.10.dist-info/DESCRIPTION.rst
onering-0.0.10.dist-info/METADATA
onering-0.0.10.dist-info/RECORD
onering-0.0.10.dist-info/WHEEL
onering-0.0.10.dist-info/metadata.json
onering-0.0.10.dist-info/top_level.txt
